{"0": {"1": {"text": "01", "type": "Execs"}, "2": {"text": "02", "type": "Execs"}, "3": {"text": "03", "type": "Execs"}, "4": {"text": "04", "type": "Execs"}, "0": {"text": "00", "type": "ExecHome"}}, "1": {"1": {"text": "11", "type": "Gallery", "src": "IMG_1559.JPG"}, "2": {"text": "12", "type": "Gallery", "src": "IMG_1560.JPG"}, "3": {"text": "13", "type": "Gallery", "src": "IMG_1562.JPG"}, "4": {"text": "14", "type": "Gallery", "src": "IMG_1564.JPG"}, "5": {"text": "15", "type": "Gallery", "src": "IMG_1570.JPG"}, "6": {"text": "16", "type": "Gallery", "src": "IMG_1574.JPG"}, "7": {"text": "17", "type": "Gallery", "src": "IMG_1575.JPG"}, "8": {"text": "18", "type": "Gallery", "src": "IMG_1582.JPG"}, "9": {"text": "19", "type": "Gallery", "src": "IMG_1586.JPG"}, "10": {"text": "110", "type": "Gallery", "src": "IMG_1587.JPG"}, "11": {"text": "111", "type": "Gallery", "src": "IMG_1589.JPG"}, "12": {"text": "112", "type": "Gallery", "src": "IMG_1594.JPG"}, "13": {"text": "113", "type": "Gallery", "src": "IMG_1596.JPG"}, "14": {"text": "114", "type": "Gallery", "src": "IMG_1600.JPG"}, "15": {"text": "115", "type": "Gallery", "src": "IMG_1604.JPG"}, "16": {"text": "116", "type": "Gallery", "src": "IMG_1606.JPG"}, "17": {"text": "117", "type": "Gallery", "src": "IMG_1608.JPG"}, "18": {"text": "118", "type": "Gallery", "src": "IMG_1613.JPG"}, "19": {"text": "119", "type": "Gallery", "src": "IMG_1614.JPG"}, "20": {"text": "120", "type": "Gallery", "src": "IMG_1616.JPG"}, "21": {"text": "121", "type": "Gallery", "src": "IMG_1619.JPG"}, "22": {"text": "122", "type": "Gallery", "src": "IMG_1620.JPG"}, "23": {"text": "123", "type": "Gallery", "src": "IMG_1623.JPG"}, "24": {"text": "124", "type": "Gallery", "src": "IMG_1625.JPG"}, "25": {"text": "125", "type": "Gallery", "src": "IMG_1627.JPG"}, "26": {"text": "126", "type": "Gallery", "src": "IMG_1628.JPG"}, "27": {"text": "127", "type": "Gallery", "src": "IMG_1630.JPG"}, "28": {"text": "128", "type": "Gallery", "src": "IMG_1632.JPG"}, "29": {"text": "129", "type": "Gallery", "src": "IMG_1633.JPG"}, "30": {"text": "130", "type": "Gallery", "src": "IMG_1636.JPG"}, "31": {"text": "131", "type": "Gallery", "src": "IMG_1637.JPG"}, "32": {"text": "132", "type": "Gallery", "src": "IMG_1639.JPG"}, "0": {"text": "10", "type": "GalleryHome"}}, "2": {"0": {"text": "20", "type": "InfoHome"}}, "3": {"0": {"text": "30", "type": "OtherHome"}}}